SmoothPrint/Smooth.py
SmoothPrint/__init__.py
SmoothPrint-1.0.2.dist-info/LICENSE
SmoothPrint-1.0.2.dist-info/METADATA
SmoothPrint-1.0.2.dist-info/WHEEL
SmoothPrint-1.0.2.dist-info/top_level.txt
SmoothPrint-1.0.2.dist-info/RECORD
