Metadata-Version: 2.1
Name: SmoothPrint
Version: 1.0.2
Summary: A small example package
Home-page: https://github.com/Blauker/SmoothPrint
Author: Blauker
Author-email: blauker.contact@gmail.com
Project-URL: Bug Tracker, https://github.com/Blauker/SmoothPrint/issues
Classifier: Programming Language :: Python :: 3
Classifier: License :: OSI Approved :: MIT License
Classifier: Operating System :: OS Independent
Requires-Python: >=3.10
License-File: LICENSE
